wolfram_model_version.py
wolfram_model/__init__.py
wolfram_model/_wolfram_model.cpython-37m-darwin.so
wolfram_model/vis/__init__.py
wolfram_model/vis/fixture.py
wolfram_model/vis/vis.py
wolfram_model/vis/networkx/__init__.py
wolfram_model/vis/networkx/vis.py
wolfram_model-0.3.15.0.dist-info/METADATA
wolfram_model-0.3.15.0.dist-info/WHEEL
wolfram_model-0.3.15.0.dist-info/top_level.txt
wolfram_model-0.3.15.0.dist-info/RECORD
