Metadata-Version: 2.1
Name: wolfram-model
Version: 0.3.15.0
Summary: wolfram_model is a toolkit to explore Set Substitution Systems (Wolfram Models)
Home-page: https://github.com/phcerdan/wolfram_model
Author: Pablo Hernandez-Cerdan
Author-email: pablo.hernandez.cerdan@outlook.com
License: MIT
Download-URL: https://github.com/phcerdan/wolfram_model
Keywords: wolfram_model physics graph complex_networks unifying relativity quantum
Platform: UNKNOWN
Classifier: License :: OSI Approved :: MIT License
Classifier: Programming Language :: Python
Classifier: Programming Language :: C++
Classifier: Development Status :: 4 - Beta
Classifier: Intended Audience :: Developers
Classifier: Intended Audience :: Education
Classifier: Intended Audience :: Science/Research
Classifier: Topic :: Scientific/Engineering
Classifier: Topic :: Scientific/Engineering :: Physics
Classifier: Topic :: Scientific/Engineering :: Mathematics
Classifier: Topic :: Scientific/Engineering :: Information Analysis
Classifier: Topic :: Software Development :: Libraries
Classifier: Operating System :: Android
Classifier: Operating System :: Microsoft :: Windows
Classifier: Operating System :: POSIX
Classifier: Operating System :: Unix
Classifier: Operating System :: MacOS
